cached_file_fetcher/__init__.py
cached_file_fetcher-0.0.5.dist-info/LICENSE
cached_file_fetcher-0.0.5.dist-info/METADATA
cached_file_fetcher-0.0.5.dist-info/WHEEL
cached_file_fetcher-0.0.5.dist-info/top_level.txt
cached_file_fetcher-0.0.5.dist-info/RECORD
