Metadata-Version: 2.1
Name: cached-file-fetcher
Version: 0.0.5
Summary: Fetches files from s3, and caches them on local disk while maintaining a size-limited LRU cache.
Author-email: TuneFlow <contact@info.tuneflow.com>
Project-URL: Homepage, https://github.com/andantei/file-fetcher
Project-URL: Bug Tracker, https://github.com/andantei/file-fetcher/issues
Keywords: file,fetcher
Classifier: Programming Language :: Python :: 3
Classifier: License :: OSI Approved :: MIT License
Classifier: Operating System :: OS Independent
Requires-Python: >=3.7
License-File: LICENSE
Requires-Dist: boto3 (>=1.26.151)
Requires-Dist: lru-dict (>=1.2.0)
